b2tsf/__init__.py
b2tsf/belle_CDC_canvas.py
b2tsf/belle_CDC_frame.py
b2tsf/belle_CDC_layer.py
b2tsf/belle_CDC_sequence.py
b2tsf/lut_config.py
b2tsf/merger_processor_ref_testbench_writer.py
b2tsf/merger_processor_stimuli_testbench_writer.py
b2tsf/testbench_writer_factory.py
b2tsf/track_segment_finder.py
b2tsf/track_segment_finder_LUT12.py
b2tsf/track_segment_finder_LUT5.py
b2tsf/track_segment_finder_LUT9.py
b2tsf/track_segment_finder_hourglas.py
b2tsf/tsf_processor_ref_testbench_writer.py
b2tsf/tsf_processor_stimuli_testbench_writer.py
b2tsf/data/innerLRLUT.mif
b2tsf/data/outerLRLUT.mif
b2tsf/data/tsf_coordinates_translation.txt
b2tsf-0.6.8.4.dist-info/LICENSE
b2tsf-0.6.8.4.dist-info/METADATA
b2tsf-0.6.8.4.dist-info/WHEEL
b2tsf-0.6.8.4.dist-info/top_level.txt
b2tsf-0.6.8.4.dist-info/RECORD
