Metadata-Version: 2.1
Name: b2tsf
Version: 0.6.8.4
Summary: A simulation framework to develop, visualize and test new track segment finder algorithms.
Home-page: https://gitlab.itiv.kit.edu/urobx/belle2-tsf-simulation
Author: Marc Neu
Author-email: marc.neu@gmx.net
License: UNKNOWN
Platform: UNKNOWN
Classifier: Programming Language :: Python :: 3
Classifier: License :: OSI Approved :: MIT License
Classifier: Operating System :: OS Independent
Requires-Python: >=3.6
License-File: LICENSE
Requires-Dist: numpy
Requires-Dist: pandas
Requires-Dist: bitarray
Requires-Dist: plotly
Requires-Dist: setuptools
